{
	"info": {
		"_postman_id": "dd8dcdec-e9f7-40a9-a761-894fe7988289",
		"name": "FP Alpha Tech Test",
		"schema": "https://schema.getpostman.com/json/collection/v2.0.0/collection.json",
		"_exporter_id": "26785541",
		"_collection_link": "https://risky-team.postman.co/workspace/My-Risky-Measurer-API~ebb152bb-1ed7-480a-a772-de2dafb97099/collection/26785541-dd8dcdec-e9f7-40a9-a761-894fe7988289?action=share&source=collection_link&creator=26785541"
	},
	"item": [
		{
			"name": "Ping",
			"request": {
				"method": "GET",
				"header": [],
				"url": "http://localhost:5000/api/ping"
			},
			"response": []
		},
		{
			"name": "GET JSON from raw data",
			"event": [
				{
					"listen": "prerequest",
					"script": {
						"exec": [
							"pm.environment.set('text_one', '{\"will\": [{\"familyRelationships\": [{\"name\": \"Joan Cook\",\"relationship\": \"Self\"},{\"name\": \"Kelly Cook\",\"relationship\": \"Spouse\"},{\"name\": \"Evelyn Cook\",\"relationship\": \"Child\"},{\"name\": \"Walter Cook\",\"relationship\": \"Child\"},{\"name\": \"Stephen Cook\",\"relationship\": \"Child\"}],\"title\": {\"value\": \"\"},\"executor\": [\"Kelly Cook\"],\"replacement_executor\": [\"Roy Cook\"],\"guardian\": [\"Roy Cook\"],\"state\": [\"California\"],\"willOwner\": {\"value\": \"Joan Cook\"},\"dateOfWill\": {\"value\": \"03/10/2022\"},\"assets\": [{\"assetName\": \"Residuary estate\",\"assetType\": \"Residuary Estate\",\"primaryBeneficiaries\": [{\"whenWillTransfer\": \"Upon death of Will Owner\",\"isItFirstDeathOrSecondDeath\": \"First death\",\"beneficiaries\": [{\"name\": \"Evelyn Cook\",\"value\": \"%\",\"amount\": \"33\",\"comment\": \"If he survives the testator\"},{\"name\": \"Walter Cook\",\"value\": \"%\",\"amount\": \"33\",\"comment\": \"If she survives the testator\"},{\"name\": \"Stephen Cook\",\"value\": \"%\",\"amount\": \"33\",\"comment\": \"Charitable contribution\"}]}]}],\"materialInformation\": [{\"value\": \"Lorem ipsum dolor sit amet, consectetur adipiscing elit.\",\"page\": \"\",\"paragraph\": \"\"},{\"value\": \"Sed luctus purus ac quam feugiat, bibendum dignissim mauris fringilla.\",\"page\": \"\",\"paragraph\": \"\"},{\"value\": \"Quisque sodales libero quis dui ultricies aliquet nec dignissim metus.\",\"page\": \"\",\"paragraph\": \"1\"},{\"value\": \"Pellentesque pharetra metus ac risus pulvinar, non pretium odio laoreet.\",\"page\": \"\",\"paragraph\": \"1\"}],\"isItAPouroverWill\": \"No\",\"whichPouroverTrust\": \"\",\"areThereTestamentaryTrusts\": \"No\",\"whichTestamentaryTrust\": \"\"}],\"trusts\": [{\"familyRelationships\": [{\"name\": \"Marilyn Cook\",\"relationship\": \"Family member\"},{\"name\": \"Ralph Reed\",\"relationship\": \"Spouse\"},{\"name\": \"Roy Cook\",\"relationship\": \"Family member\"},{\"name\": \"Joan Cook\",\"relationship\": \"Self\"}],\"title\": {\"value\": \"Joan Cook Trust\"},\"dateOfTrust\": \"\",\"grantor\": [\"Kelly Cook\"],\"trustee\": [{\"name\": \"Joan Cook\",\"relation\": \"Self\",\"trusteeType\": \"trustee\",\"trusteeTrusteeOrCoTrustee\": \"Trustee\",\"trusteeCanTrusteesActIndividually\": \"Yes\",\"trusteeCanAnyCoTrusteeContinueAsSoleTrustee\": \"Yes\",\"page\": \"\",\"paragraph\": \"ARTICLE SECOND APPOINTMENT OF TRUSTEES A. Original Trustees.\"},{\"name\": \"Kelly Cook\",\"relation\": \"Unspecified\",\"trusteeType\": \"successive_trustee\",\"trusteeTrusteeOrCoTrustee\": \"Trustee\",\"trusteeCanTrusteesActIndividually\": \"Yes\",\"trusteeCanAnyCoTrusteeContinueAsSoleTrustee\": \"Yes\",\"page\": \"\",\"paragraph\": \"ARTICLE SECOND APPOINTMENT OF TRUSTEES B. Successors.\"}],\"successor_trustee\": [],\"type\": \"Revocable\",\"state\": [\"California\"],\"assets\": [{\"assetName\": \"Residuary Trust estate\",\"assetType\": \"Residuary Estate\",\"primaryBeneficiaries\": [{\"whenWillTransfer\": \"Upon death of Trust Owner\",\"isItFirstDeathOrSecondDeath\": \"First death\",\"beneficiaries\": [{\"name\": \"Kelly Cook\",\"value\": \"%\",\"amount\": \"25\",\"comment\": \"If he does not survive the Grantor, then this distribution shall lapse\"},{\"name\": \"Evelyn Cook\",\"value\": \"%\",\"amount\": \"25\",\"comment\": \"If she does not survive the Grantor, then this distribution shall lapse\"},{\"name\": \"Walter Cook\",\"value\": \"%\",\"amount\": \"25\",\"comment\": \"If she does not survive the Grantor, then this distribution shall lapse\"},{\"name\": \"Stephen Cook\",\"value\": \"%\",\"amount\": \"25\",\"comment\": \"To be distributed jointly with TERESE KARAMBELAS, or all to the survivor of them\"}]}]}],\"trustees\": [{\"name\": \"Joan Cook\",\"relation\": \"Self\",\"trusteeType\": \"trustee\",\"trusteeTrusteeOrCoTrustee\": \"Trustee\",\"trusteeCanTrusteesActIndividually\": \"Yes\",\"trusteeCanAnyCoTrusteeContinueAsSoleTrustee\": \"Yes\",\"page\": \"\",\"paragraph\": \"ARTICLE SECOND APPOINTMENT OF TRUSTEES A. Original Trustees.\"},{\"name\": \"Kelly Cook\",\"relation\": \"Unspecified\",\"trusteeType\": \"successive_trustee\",\"trusteeTrusteeOrCoTrustee\": \"Trustee\",\"trusteeCanTrusteesActIndividually\": \"Yes\",\"trusteeCanAnyCoTrusteeContinueAsSoleTrustee\": \"Yes\",\"page\": \"\",\"paragraph\": \"ARTICLE SECOND APPOINTMENT OF TRUSTEES B. Successors.\"}],\"subtype\": \"General Revocable Outright\",\"jointOrSingle\": \"Single\",\"grantorOrNonGrantorTrust\": \"No\",\"resultingTrusts\": \"\",\"listsAssets\": \"Yes\",\"materialInformation\": [{\"value\": \"Integer auctor velit sit amet eros dapibus, eu faucibus metus elementum.\",\"page\": \"\",\"paragraph\": \"\"},{\"value\": \"Nulla finibus felis sit amet lectus rutrum, sit amet sagittis dolor congue.\",\"page\": \"\",\"paragraph\": \"ARTICLE FIRST\"},{\"value\": \"Nunc tempus justo eget ex tempus, vitae tincidunt neque tincidunt.\",\"page\": \"\",\"paragraph\": \"ARTICLE SECOND\"},{\"value\": \"Suspendisse tempor metus volutpat justo rhoncus, nec suscipit odio tempus.\",\"page\": \"\",\"paragraph\": \"ARTICLE FOURTH B\"}]}]}');\r",
							"\r",
							"pm.environment.set('text_two', '{\"will\": [{\"familyRelationships\": [{\"name\": \"Joan Cook\",\"relationship\": \"Self\"},{\"name\": \"Kelly Cook\",\"relationship\": \"Spouse\"},{\"name\": \"Evelyn Cook\",\"relationship\": \"Child\"},{\"name\": \"Walter Cook\",\"relationship\": \"Child\"},{\"name\": \"Stephen Cook\",\"relationship\": \"Child\"}],\"title\": {\"value\": \"\"},\"executor\": [\"Kelly Cook\"],\"replacement_executor\": [\"Roy Cook\"],\"guardian\": [\"Roy Cook\"],\"state\": [\"California\"],\"willOwner\": {\"value\": None},\"dateOfWill\": {\"value\": \"03/10/2022\"},\"assets\": [{\"assetName\": \"Residuary estate\",\"assetType\": \"Residuary Estate\",\"primaryBeneficiaries\": [{\"whenWillTransfer\": \"Upon death of Will Owner\",\"isItFirstDeathOrSecondDeath\": \"First death\",\"beneficiaries\": [{\"name\": \"Evelyn Cook\",\"value\": \"%\",\"amount\": \"33\",\"comment\": \"If he survives the testator\"},{\"name\": \"Walter Cook\",\"value\": \"%\",\"amount\": \"33\",\"comment\": \"If she survives the testator\"},{\"name\": \"Stephen Cook\",\"value\": \"%\",\"amount\": \"33\",\"comment\": \"Charitable contribution\"}]}]}],\"materialInformation\": [{\"value\": \"Lorem ipsum dolor sit amet, consectetur adipiscing elit.\",\"page\": \"\",\"paragraph\": \"\"},{\"value\": \"Sed luctus purus ac quam feugiat, bibendum dignissim mauris fringilla.\",\"page\": \"\",\"paragraph\": \"\"},{\"value\": \"Quisque sodales libero quis dui ultricies aliquet nec dignissim metus.\",\"page\": \"\",\"paragraph\": \"1\"},{\"value\": \"Pellentesque pharetra metus ac risus pulvinar, non pretium odio laoreet.\",\"page\": None,\"paragraph\": \"1\"}],\"isItAPouroverWill\": \"No\",\"whichPouroverTrust\": \"\",\"areThereTestamentaryTrusts\": \"No\",\"whichTestamentaryTrust\": \"\"}],\"trusts\": [{\"familyRelationships\": [{\"name\": \"Marilyn Cook\",\"relationship\": \"Family member\"},{\"name\": \"Ralph Reed\",\"relationship\": \"Spouse\"},{\"name\": \"Roy Cook\",\"relationship\": \"Family member\"},{\"name\": \"Joan Cook\",\"relationship\": \"Self\"}],\"title\": {\"value\": \"Joan Cook Trust\"},\"dateOfTrust\": \"\",\"grantor\": [\"Kelly Cook\"],\"trustee\": [{\"name\": \"Joan Cook\",\"relation\": \"Self\",\"trusteeType\": \"trustee\",\"trusteeTrusteeOrCoTrustee\": \"Trustee\",\"trusteeCanTrusteesActIndividually\": \"Yes\",\"trusteeCanAnyCoTrusteeContinueAsSoleTrustee\": \"Yes\",\"page\": \"\",\"paragraph\": \"ARTICLE SECOND APPOINTMENT OF TRUSTEES A. Original Trustees.\"},{\"name\": \"Kelly Cook\",\"relation\": \"Unspecified\",\"trusteeType\": \"successive_trustee\",\"trusteeTrusteeOrCoTrustee\": \"Trustee\",\"trusteeCanTrusteesActIndividually\": \"Yes\",\"trusteeCanAnyCoTrusteeContinueAsSoleTrustee\": \"Yes\",\"page\": \"\",\"paragraph\": \"ARTICLE SECOND APPOINTMENT OF TRUSTEES B. Successors.\"}],\"successor_trustee\": [],\"type\": \"Revocable\",\"state\": [\"California\"],\"assets\": [{\"assetName\": \"Residuary Trust estate\",\"assetType\": \"Residuary Estate\",\"primaryBeneficiaries\": [{\"whenWillTransfer\": \"Upon death of Trust Owner\",\"isItFirstDeathOrSecondDeath\": \"First death\",\"beneficiaries\": [{\"name\": \"Kelly Cook\",\"value\": \"%\",\"amount\": \"25\",\"comment\": \"If he does not survive the Grantor, then this distribution shall lapse\"},{\"name\": \"Evelyn Cook\",\"value\": \"%\",\"amount\": \"25\",\"comment\": \"If she does not survive the Grantor, then this distribution shall lapse\"},{\"name\": \"Walter Cook\",\"value\": \"%\",\"amount\": \"25\",\"comment\": \"If she does not survive the Grantor, then this distribution shall lapse\"},{\"name\": \"Stephen Cook\",\"value\": \"%\",\"amount\": \"25\",\"comment\": \"To be distributed jointly with TERESE KARAMBELAS, or all to the survivor of them\"}]}]}],\"trustees\": [{\"name\": \"Joan Cook\",\"relation\": \"Self\",\"trusteeType\": \"trustee\",\"trusteeTrusteeOrCoTrustee\": \"Trustee\",\"trusteeCanTrusteesActIndividually\": \"Yes\",\"trusteeCanAnyCoTrusteeContinueAsSoleTrustee\": \"Yes\",\"page\": \"\",\"paragraph\": \"ARTICLE SECOND APPOINTMENT OF TRUSTEES A. Original Trustees.\"},{\"name\": \"Kelly Cook\",\"relation\": \"Unspecified\",\"trusteeType\": \"successive_trustee\",\"trusteeTrusteeOrCoTrustee\": \"Trustee\",\"trusteeCanTrusteesActIndividually\": \"Yes\",\"trusteeCanAnyCoTrusteeContinueAsSoleTrustee\": \"Yes\",\"page\": \"\",\"paragraph\": \"ARTICLE SECOND APPOINTMENT OF TRUSTEES B. Successors.\"}],\"subtype\": \"General Revocable Outright\",\"jointOrSingle\": \"Single\",\"grantorOrNonGrantorTrust\": \"No\",\"resultingTrusts\": \"\",\"listsAssets\": \"Yes\",\"materialInformation\": [{\"value\": \"Integer auctor velit sit amet eros dapibus, eu faucibus metus elementum.\",\"page\": \"\",\"paragraph\": \"\"},{\"value\": \"Nulla finibus felis sit amet lectus rutrum, sit amet sagittis dolor congue.\",\"page\": \"\",\"paragraph\": \"ARTICLE FIRST\"},{\"value\": \"Nunc tempus justo eget ex tempus, vitae tincidunt neque tincidunt.\",\"page\": \"\",\"paragraph\": \"ARTICLE SECOND\"},{\"value\": \"Suspendisse tempor metus volutpat justo rhoncus, nec suscipit odio tempus.\",\"page\": \"\",\"paragraph\": \"ARTICLE FOURTH B\"}]}]}');\r",
							"\r",
							"pm.environment.set('text_three', '\"\"\"```JSON\\n{\\n    \"will\": [\\n        {\\n            \"familyRelationships\": [\\n                {\\n                    \"name\": \"Joan Cook\",\\n                    \"relationship\": \"Self\"\\n                },\\n                {\\n                    \"name\": \"Kelly Cook\",\\n                    \"relationship\": \"Spouse\"\\n                },\\n                {\\n                    \"name\": \"Evelyn Cook\",\\n                    \"relationship\": \"Child\"\\n                },\\n                {\\n                    \"name\": \"Walter Cook\",\\n                    \"relationship\": \"Child\"\\n                },\\n                {\\n                    \"name\": \"Stephen Cook\",\\n                    \"relationship\": \"Child\"\\n                }\\n            ],\\n            \"title\": {\\n                \"value\": \"\"\\n            },\\n            \"executor\": [\\n                \"Kelly Cook\"\\n            ],\\n            \"replacement_executor\": [\\n                \"Roy Cook\"\\n            ],\\n            \"guardian\": [\\n                \"Roy Cook\"\\n            ],\\n            \"state\": [\\n                \"California\"\\n            ],\\n            \"willOwner\": {\\n                \"value\": \"Joan Cook\"\\n            },\\n            \"dateOfWill\": {\\n                \"value\": \"03/10/2022\"\\n            },\\n            \"assets\": [\\n                {\\n                    \"assetName\": \"Residuary estate\",\\n                    \"assetType\": \"Residuary Estate\",\\n                    \"primaryBeneficiaries\": [\\n                        {\\n                            \"whenWillTransfer\": \"Upon death of Will Owner\",\\n                            \"isItFirstDeathOrSecondDeath\": \"First death\",\\n                            \"beneficiaries\": [\\n                                {\\n                                    \"name\": \"Evelyn Cook\",\\n                                    \"value\": \"%\",\\n                                    \"amount\": \"33\",\\n                                    \"comment\": \"If he survives the testator\"\\n                                },\\n                                {\\n                                    \"name\": \"Walter Cook\",\\n                                    \"value\": \"%\",\\n                                    \"amount\": \"33\",\\n                                    \"comment\": \"If she survives the testator\"\\n                                },\\n                                {\\n                                    \"name\": \"Stephen Cook\",\\n                                    \"value\": \"%\",\\n                                    \"amount\": \"33\",\\n                                    \"comment\": \"Charitable contribution\"\\n                                }\\n                            ]\\n                        }\\n                    ]\\n                }\\n            ],\\n            \"materialInformation\": [\\n                {\\n                    \"value\": \"Lorem ipsum dolor sit amet, consectetur adipiscing elit.\",\\n                    \"page\": \"\",\\n                    \"paragraph\": \"\"\\n                },\\n                {\\n                    \"value\": \"Sed luctus purus ac quam feugiat, bibendum dignissim mauris fringilla.\",\\n                    \"page\": \"\",\\n                    \"paragraph\": \"\"\\n                },\\n                {\\n                    \"value\": \"Quisque sodales libero quis dui ultricies aliquet nec dignissim metus.\",\\n                    \"page\": \"\",\\n                    \"paragraph\": \"1\"\\n                },\\n                {\\n                    \"value\": \"Pellentesque pharetra metus ac risus pulvinar, non pretium odio laoreet.\",\\n                    \"page\": \"\",\\n                    \"paragraph\": \"1\"\\n                }\\n            ],\\n            \"isItAPouroverWill\": \"No\",\\n            \"whichPouroverTrust\": \"\",\\n            \"areThereTestamentaryTrusts\": \"No\",\\n            \"whichTestamentaryTrust\": \"\"\\n        }\\n    ],\\n    \"trusts\": [\\n        {\\n            \"familyRelationships\": [\\n                {\\n                    \"name\": \"Marilyn Cook\",\\n                    \"relationship\": \"Family member\"\\n                },\\n                {\\n                    \"name\": \"Ralph Reed\",\\n                    \"relationship\": \"Spouse\"\\n                },\\n                {\\n                    \"name\": \"Roy Cook\",\\n                    \"relationship\": \"Family member\"\\n                },\\n                {\\n                    \"name\": \"Joan Cook\",\\n                    \"relationship\": \"Self\"\\n                }\\n            ],\\n            \"title\": {\\n                \"value\": \"Joan Cook Trust\"\\n            },\\n            \"dateOfTrust\": \"\",\\n            \"grantor\": [\\n                \"Kelly Cook\"\\n            ],\\n            \"trustee\": [\\n                {\\n                    \"name\": \"Joan Cook\",\\n                    \"relation\": \"Self\",\\n                    \"trusteeType\": \"trustee\",\\n                    \"trusteeTrusteeOrCoTrustee\": \"Trustee\",\\n                    \"trusteeCanTrusteesActIndividually\": \"Yes\",\\n                    \"trusteeCanAnyCoTrusteeContinueAsSoleTrustee\": \"Yes\",\\n                    \"page\": \"\",\\n                    \"paragraph\": \"ARTICLE SECOND APPOINTMENT OF TRUSTEES A. Original Trustees.\"\\n                },\\n                {\\n                    \"name\": \"Kelly Cook\",\\n                    \"relation\": \"Unspecified\",\\n                    \"trusteeType\": \"successive_trustee\",\\n                    \"trusteeTrusteeOrCoTrustee\": \"Trustee\",\\n                    \"trusteeCanTrusteesActIndividually\": \"Yes\",\\n                    \"trusteeCanAnyCoTrusteeContinueAsSoleTrustee\": \"Yes\",\\n                    \"page\": \"\",\\n                    \"paragraph\": \"ARTICLE SECOND APPOINTMENT OF TRUSTEES B. Successors.\"\\n                }\\n            ],\\n            \"successor_trustee\": [],\\n            \"type\": \"Revocable\",\\n            \"state\": [\\n                \"California\"\\n            ],\\n            \"assets\": [\\n                {\\n                    \"assetName\": \"Residuary Trust estate\",\\n                    \"assetType\": \"Residuary Estate\",\\n                    \"primaryBeneficiaries\": [\\n                        {\\n\"whenWillTransfer\": \"Upon death of Trust Owner\",\\n                            \"isItFirstDeathOrSecondDeath\": \"First death\",\\n                            \"beneficiaries\": [\\n                                {\\n                                    \"name\": \"Kelly Cook\",\\n\"value\": \"%\",\\n                                    \"amount\": \"25\",\\n                                    \"comment\": \"If he does not survive the Grantor, then this distribution shall lapse\"\\n                                },\\n                                {\\n\"name\": \"Evelyn Cook\",\\n                                    \"value\": \"%\",\\n                                    \"amount\": \"25\",\\n                                    \"comment\": \"If she does not survive the Grantor, then this distribution shall lapse\"\\n},\\n                                {\\n                                    \"name\": \"Walter Cook\",\\n                                    \"value\": \"%\",\\n                                    \"amount\": \"25\",\\n                                    \"comment\": \"If she does not survive the Grantor, then this distribution shall lapse\"\\n                                },\\n                                {\\n                                    \"name\": \"Stephen Cook\",\\n                                    \"value\": \"%\",\\n                                    \"amount\": \"25\",\\n\"comment\": \"To be distributed jointly with TERESE KARAMBELAS, or all to the survivor of them\"\\n                                }\\n                            ]\\n                        }\\n                    ]\\n                }\\n            ],\\n            \"trustees\": [\\n{\\n                    \"name\": \"Joan Cook\",\\n                    \"relation\": \"Self\",\\n                    \"trusteeType\": \"trustee\",\\n\"trusteeTrusteeOrCoTrustee\": \"Trustee\",\\n                    \"trusteeCanTrusteesActIndividually\": \"Yes\",\\n                    \"trusteeCanAnyCoTrusteeContinueAsSoleTrustee\": \"Yes\",\\n                    \"page\": \"\",\\n                    \"paragraph\": \"ARTICLE SECOND APPOINTMENT OF TRUSTEES A. Original Trustees.\"\\n                },\\n                {\\n                    \"name\": \"Kelly Cook\",\\n                    \"relation\": \"Unspecified\",\\n                    \"trusteeType\": \"successive_trustee\",\\n                    \"trusteeTrusteeOrCoTrustee\": \"Trustee\",\\n                    \"trusteeCanTrusteesActIndividually\": \"Yes\",\\n                    \"trusteeCanAnyCoTrusteeContinueAsSoleTrustee\": \"Yes\",\\n                    \"page\": \"\",\\n                    \"paragraph\": \"ARTICLE SECOND APPOINTMENT OF TRUSTEES B. Successors.\"\\n                }\\n            ],\\n            \"subtype\": \"General Revocable Outright\",\\n            \"jointOrSingle\": \"Single\",\\n            \"grantorOrNonGrantorTrust\": \"No\",\\n            \"resultingTrusts\": \"\",\\n            \"listsAssets\": \"Yes\",\\n            \"materialInformation\": [\\n                {\\n                    \"value\": \"Integer auctor velit sit amet eros dapibus, eu faucibus metus elementum.\",\\n                    \"page\": \"\",\\n                    \"paragraph\": \"\"\\n                },\\n                {\\n                    \"value\": \"Nulla finibus felis sit amet lectus rutrum, sit amet sagittis dolor congue.\",\\n\"page\": \"\",\\n                    \"paragraph\": \"ARTICLE FIRST\"\\n                },\\n                {\\n                    \"value\": \"Nunc tempus justo eget ex tempus, vitae tincidunt neque tincidunt.\",\\n                    \"page\": \"\",\\n                    \"paragraph\": \"ARTICLE SECOND\"\\n                },\\n                {\\n                    \"value\": \"Suspendisse tempor metus volutpat justo rhoncus, nec suscipit odio tempus.\",\\n\"page\": \"\",\\n                    \"paragraph\": \"ARTICLE FOURTH B\"\\n                }\\n            ]\\n        }\\n    ]\\n}\\n', '', '', '', '\\n\\nLorem ipsum dolor sit amet, consectetur adipiscing elit. Suspendisse in libero ultrices, pretium tellus at, dapibus eros. Sed scelerisque vel sem non faucibus. Integer ornare, odio quis eleifend scelerisque, leo diam viverra sapien, fringilla semper ligula mauris nec erat. Sed tincidunt dui eu velit gravida tempus. Proin sit amet dictum mi. Suspendisse semper, quam nec hendrerit euismod, nisi risus molestie dui, non facilisis odio ex quis libero. Vestibulum accumsan sed tortor nec luctus. Aliquam tortor libero, luctus eget tortor ut, rutrum faucibus tortor. Maecenas non vehicula sem. \\n```\"\"\"');\r",
							"\r",
							"pm.environment.set('text_four', '{\"will\": [{\"familyRelationships\": [{\"name\": \"Joan Cook\",\"relationship\": \"Self\"},{\"name\": \"Kelly Cook\",\"relationship\": \"Spouse\"},{\"name\": \"Evelyn Cook\",\"relationship\": \"Child\"},{\"name\": \"Walter Cook\",\"relationship\": \"Child\"},{\"name\": \"Stephen Cook\",\"relationship\": \"Child\"}],\"title\": {\"value\": \"\"},\"executor\": [\"Kelly Cook\"],\"replacement_executor\": [\"Roy Cook\"],\"guardian\": [\"Roy Cook\"],\"state\": [\"California\"],\"willOwner\": {\"value\": None},\"dateOfWill\": {\"value\": \"03/10/2022\"},\"assets\": [{\"assetName\": \"Residuary estate\",\"assetType\": \"Residuary Estate\",\"primaryBeneficiaries\": [{\"whenWillTransfer\": \"Upon death of Will Owner\",\"isItFirstDeathOrSecondDeath\": \"First death\",\"beneficiaries\": [{\"name\": \"Evelyn Cook\",\"value\": \"%\",\"amount\": \"33\",\"comment\": \"If he survives the testator\"},{\"name\": \"Walter Cook\",\"value\": \"%\",\"amount\": \"33\",\"comment\": \"If she survives the testator\"},{\"name\": \"Stephen Cook\",\"value\": \"%\",\"amount\": \"33\",\"comment\": \"Charitable contribution\"}]}]}],\"materialInformation\": [{\"value\": \"Lorem ipsum dolor sit amet, consectetur adipiscing elit.\",\"page\": \"\",\"paragraph\": \"\"},{\"value\": \"Sed luctus purus ac quam feugiat, bibendum dignissim mauris fringilla.\",\"page\": \"\",\"paragraph\": \"\"},{\"value\": \"Quisque sodales libero quis dui ultricies aliquet nec dignissim metus.\",\"page\": \"\",\"paragraph\": \"1\"},{\"value\": \"Pellentesque pharetra metus ac risus pulvinar, non pretium odio laoreet.\",\"page\": \"\",\"paragraph\": \"1\"}],\"isItAPouroverWill\": \"No\",\"whichPouroverTrust\": \"\",\"areThereTestamentaryTrusts\": \"No\",\"whichTestamentaryTrust\": \"\"}]}');"
						],
						"type": "text/javascript",
						"packages": {}
					}
				}
			],
			"protocolProfileBehavior": {
				"disableBodyPruning": true
			},
			"request": {
				"method": "GET",
				"header": [],
				"body": {
					"mode": "raw",
					"raw": "{\r\n    \"data\": {{text_one}}\r\n}",
					"options": {
						"raw": {
							"language": "json"
						}
					}
				},
				"url": "http://localhost:5000/api/json"
			},
			"response": [
				{
					"name": "New Request",
					"originalRequest": {
						"method": "GET",
						"header": [],
						"body": {
							"mode": "raw",
							"raw": "{\r\n    \"data\": {{text_one}}\r\n}",
							"options": {
								"raw": {
									"language": "json"
								}
							}
						},
						"url": "http://localhost:5000/api/json"
					},
					"status": "OK",
					"code": 200,
					"_postman_previewlanguage": "json",
					"header": [
						{
							"key": "Server",
							"value": "Werkzeug/3.0.3 Python/3.11.3"
						},
						{
							"key": "Date",
							"value": "Fri, 10 May 2024 07:11:11 GMT"
						},
						{
							"key": "Content-Type",
							"value": "application/json"
						},
						{
							"key": "Content-Length",
							"value": "4478"
						},
						{
							"key": "Connection",
							"value": "close"
						}
					],
					"cookie": [],
					"body": "{\n    \"data\": {\n        \"trusts\": [\n            {\n                \"assets\": [\n                    {\n                        \"assetName\": \"Residuary Trust estate\",\n                        \"assetType\": \"Residuary Estate\",\n                        \"primaryBeneficiaries\": [\n                            {\n                                \"beneficiaries\": [\n                                    {\n                                        \"amount\": \"25\",\n                                        \"comment\": \"If he does not survive the Grantor, then this distribution shall lapse\",\n                                        \"name\": \"Kelly Cook\",\n                                        \"value\": \"%\"\n                                    },\n                                    {\n                                        \"amount\": \"25\",\n                                        \"comment\": \"If she does not survive the Grantor, then this distribution shall lapse\",\n                                        \"name\": \"Evelyn Cook\",\n                                        \"value\": \"%\"\n                                    },\n                                    {\n                                        \"amount\": \"25\",\n                                        \"comment\": \"If she does not survive the Grantor, then this distribution shall lapse\",\n                                        \"name\": \"Walter Cook\",\n                                        \"value\": \"%\"\n                                    },\n                                    {\n                                        \"amount\": \"25\",\n                                        \"comment\": \"To be distributed jointly with TERESE KARAMBELAS, or all to the survivor of them\",\n                                        \"name\": \"Stephen Cook\",\n                                        \"value\": \"%\"\n                                    }\n                                ],\n                                \"isItFirstDeathOrSecondDeath\": \"First death\",\n                                \"whenWillTransfer\": \"Upon death of Trust Owner\"\n                            }\n                        ]\n                    }\n                ],\n                \"dateOfTrust\": \"\",\n                \"familyRelationships\": [\n                    {\n                        \"name\": \"Marilyn Cook\",\n                        \"relationship\": \"Family member\"\n                    },\n                    {\n                        \"name\": \"Ralph Reed\",\n                        \"relationship\": \"Spouse\"\n                    },\n                    {\n                        \"name\": \"Roy Cook\",\n                        \"relationship\": \"Family member\"\n                    },\n                    {\n                        \"name\": \"Joan Cook\",\n                        \"relationship\": \"Self\"\n                    }\n                ],\n                \"grantor\": [\n                    \"Kelly Cook\"\n                ],\n                \"grantorOrNonGrantorTrust\": \"No\",\n                \"jointOrSingle\": \"Single\",\n                \"listsAssets\": \"Yes\",\n                \"materialInformation\": [\n                    {\n                        \"page\": \"\",\n                        \"paragraph\": \"\",\n                        \"value\": \"Integer auctor velit sit amet eros dapibus, eu faucibus metus elementum.\"\n                    },\n                    {\n                        \"page\": \"\",\n                        \"paragraph\": \"ARTICLE FIRST\",\n                        \"value\": \"Nulla finibus felis sit amet lectus rutrum, sit amet sagittis dolor congue.\"\n                    },\n                    {\n                        \"page\": \"\",\n                        \"paragraph\": \"ARTICLE SECOND\",\n                        \"value\": \"Nunc tempus justo eget ex tempus, vitae tincidunt neque tincidunt.\"\n                    },\n                    {\n                        \"page\": \"\",\n                        \"paragraph\": \"ARTICLE FOURTH B\",\n                        \"value\": \"Suspendisse tempor metus volutpat justo rhoncus, nec suscipit odio tempus.\"\n                    }\n                ],\n                \"resultingTrusts\": \"\",\n                \"state\": [\n                    \"California\"\n                ],\n                \"subtype\": \"General Revocable Outright\",\n                \"successor_trustee\": [],\n                \"title\": {\n                    \"value\": \"Joan Cook Trust\"\n                },\n                \"trustee\": [\n                    {\n                        \"name\": \"Joan Cook\",\n                        \"page\": \"\",\n                        \"paragraph\": \"ARTICLE SECOND APPOINTMENT OF TRUSTEES A. Original Trustees.\",\n                        \"relation\": \"Self\",\n                        \"trusteeCanAnyCoTrusteeContinueAsSoleTrustee\": \"Yes\",\n                        \"trusteeCanTrusteesActIndividually\": \"Yes\",\n                        \"trusteeTrusteeOrCoTrustee\": \"Trustee\",\n                        \"trusteeType\": \"trustee\"\n                    },\n                    {\n                        \"name\": \"Kelly Cook\",\n                        \"page\": \"\",\n                        \"paragraph\": \"ARTICLE SECOND APPOINTMENT OF TRUSTEES B. Successors.\",\n                        \"relation\": \"Unspecified\",\n                        \"trusteeCanAnyCoTrusteeContinueAsSoleTrustee\": \"Yes\",\n                        \"trusteeCanTrusteesActIndividually\": \"Yes\",\n                        \"trusteeTrusteeOrCoTrustee\": \"Trustee\",\n                        \"trusteeType\": \"successive_trustee\"\n                    }\n                ],\n                \"trustees\": [\n                    {\n                        \"name\": \"Joan Cook\",\n                        \"page\": \"\",\n                        \"paragraph\": \"ARTICLE SECOND APPOINTMENT OF TRUSTEES A. Original Trustees.\",\n                        \"relation\": \"Self\",\n                        \"trusteeCanAnyCoTrusteeContinueAsSoleTrustee\": \"Yes\",\n                        \"trusteeCanTrusteesActIndividually\": \"Yes\",\n                        \"trusteeTrusteeOrCoTrustee\": \"Trustee\",\n                        \"trusteeType\": \"trustee\"\n                    },\n                    {\n                        \"name\": \"Kelly Cook\",\n                        \"page\": \"\",\n                        \"paragraph\": \"ARTICLE SECOND APPOINTMENT OF TRUSTEES B. Successors.\",\n                        \"relation\": \"Unspecified\",\n                        \"trusteeCanAnyCoTrusteeContinueAsSoleTrustee\": \"Yes\",\n                        \"trusteeCanTrusteesActIndividually\": \"Yes\",\n                        \"trusteeTrusteeOrCoTrustee\": \"Trustee\",\n                        \"trusteeType\": \"successive_trustee\"\n                    }\n                ],\n                \"type\": \"Revocable\"\n            }\n        ],\n        \"will\": [\n            {\n                \"areThereTestamentaryTrusts\": \"No\",\n                \"assets\": [\n                    {\n                        \"assetName\": \"Residuary estate\",\n                        \"assetType\": \"Residuary Estate\",\n                        \"primaryBeneficiaries\": [\n                            {\n                                \"beneficiaries\": [\n                                    {\n                                        \"amount\": \"33\",\n                                        \"comment\": \"If he survives the testator\",\n                                        \"name\": \"Evelyn Cook\",\n                                        \"value\": \"%\"\n                                    },\n                                    {\n                                        \"amount\": \"33\",\n                                        \"comment\": \"If she survives the testator\",\n                                        \"name\": \"Walter Cook\",\n                                        \"value\": \"%\"\n                                    },\n                                    {\n                                        \"amount\": \"33\",\n                                        \"comment\": \"Charitable contribution\",\n                                        \"name\": \"Stephen Cook\",\n                                        \"value\": \"%\"\n                                    }\n                                ],\n                                \"isItFirstDeathOrSecondDeath\": \"First death\",\n                                \"whenWillTransfer\": \"Upon death of Will Owner\"\n                            }\n                        ]\n                    }\n                ],\n                \"dateOfWill\": {\n                    \"value\": \"03/10/2022\"\n                },\n                \"executor\": [\n                    \"Kelly Cook\"\n                ],\n                \"familyRelationships\": [\n                    {\n                        \"name\": \"Joan Cook\",\n                        \"relationship\": \"Self\"\n                    },\n                    {\n                        \"name\": \"Kelly Cook\",\n                        \"relationship\": \"Spouse\"\n                    },\n                    {\n                        \"name\": \"Evelyn Cook\",\n                        \"relationship\": \"Child\"\n                    },\n                    {\n                        \"name\": \"Walter Cook\",\n                        \"relationship\": \"Child\"\n                    },\n                    {\n                        \"name\": \"Stephen Cook\",\n                        \"relationship\": \"Child\"\n                    }\n                ],\n                \"guardian\": [\n                    \"Roy Cook\"\n                ],\n                \"isItAPouroverWill\": \"No\",\n                \"materialInformation\": [\n                    {\n                        \"page\": \"\",\n                        \"paragraph\": \"\",\n                        \"value\": \"Lorem ipsum dolor sit amet, consectetur adipiscing elit.\"\n                    },\n                    {\n                        \"page\": \"\",\n                        \"paragraph\": \"\",\n                        \"value\": \"Sed luctus purus ac quam feugiat, bibendum dignissim mauris fringilla.\"\n                    },\n                    {\n                        \"page\": \"\",\n                        \"paragraph\": \"1\",\n                        \"value\": \"Quisque sodales libero quis dui ultricies aliquet nec dignissim metus.\"\n                    },\n                    {\n                        \"page\": \"\",\n                        \"paragraph\": \"1\",\n                        \"value\": \"Pellentesque pharetra metus ac risus pulvinar, non pretium odio laoreet.\"\n                    }\n                ],\n                \"replacement_executor\": [\n                    \"Roy Cook\"\n                ],\n                \"state\": [\n                    \"California\"\n                ],\n                \"title\": {\n                    \"value\": \"\"\n                },\n                \"whichPouroverTrust\": \"\",\n                \"whichTestamentaryTrust\": \"\",\n                \"willOwner\": {\n                    \"value\": \"Joan Cook\"\n                }\n            }\n        ]\n    },\n    \"message\": \"ok\",\n    \"status\": 200\n}"
				}
			]
		}
	]
}